lumisync/__init__.py
lumisync/connection.py
lumisync/devices.py
lumisync/lumisync.py
lumisync/config/__init__.py
lumisync/config/options.py
lumisync/gui/__init__.py
lumisync/gui/main_window.py
lumisync/gui/controllers/__init__.py
lumisync/gui/controllers/device_controller.py
lumisync/gui/controllers/sync_controller.py
lumisync/gui/dialogs/__init__.py
lumisync/gui/dialogs/add_device_dialog.py
lumisync/gui/dialogs/settings_dialog.py
lumisync/gui/resources/__init__.py
lumisync/gui/resources/icons.py
lumisync/gui/resources/icons/lightbulb-on.svg
lumisync/gui/resources/icons/music.svg
lumisync/gui/resources/icons/network.svg
lumisync/gui/resources/icons/play.svg
lumisync/gui/resources/icons/power.svg
lumisync/gui/resources/icons/refresh.svg
lumisync/gui/resources/icons/screen.svg
lumisync/gui/resources/icons/settings.svg
lumisync/gui/resources/icons/stop.svg
lumisync/gui/utils/__init__.py
lumisync/gui/utils/validators.py
lumisync/gui/utils/window_effects.py
lumisync/gui/views/__init__.py
lumisync/gui/views/devices_view.py
lumisync/gui/views/modes_view.py
lumisync/gui/views/settings_page.py
lumisync/gui/widgets/__init__.py
lumisync/gui/widgets/led_mapping_widget.py
lumisync/gui/widgets/navigation_shell.py
lumisync/sync/__init__.py
lumisync/sync/monitor.py
lumisync/sync/music.py
lumisync/utils/__init__.py
lumisync/utils/colors.py
lumisync/utils/file_operations.py
lumisync/utils/logging.py
lumisync-0.4.0.dist-info/licenses/LICENSE
lumisync-0.4.0.dist-info/METADATA
lumisync-0.4.0.dist-info/WHEEL
lumisync-0.4.0.dist-info/entry_points.txt
lumisync-0.4.0.dist-info/top_level.txt
lumisync-0.4.0.dist-info/RECORD
