Metadata-Version: 2.4
Name: lumisync
Version: 0.4.0
Summary: A Python library for syncing Govee led strips with audio and screen content.
License: MIT License
Project-URL: repository, https://github.com/Minlor/LumiSync.git
Classifier: Development Status :: 3 - Alpha
Classifier: License :: OSI Approved :: MIT License
Classifier: Natural Language :: English
Classifier: Operating System :: Microsoft :: Windows
Classifier: Programming Language :: Python :: 3
Classifier: Programming Language :: Python :: 3.11
Classifier: Programming Language :: Python :: 3.12
Classifier: Programming Language :: Python :: 3.13
Requires-Python: >=3.11
License-File: LICENSE
Requires-Dist: colorama>=0.4.6
Requires-Dist: colour>=0.1.5
Requires-Dist: dxcam>=0.0.5
Requires-Dist: matplotlib>=3.10.1
Requires-Dist: numpy>=2.2.4
Requires-Dist: pillow>=11.1.0
Requires-Dist: soundcard>=0.4.4
Requires-Dist: webcolors>=24.11.1
Requires-Dist: PyQt6>=6.6.0
Requires-Dist: qt-material>=2.14
Requires-Dist: pywin32>=310; sys_platform == "win32"
Requires-Dist: mss>=10.1.0; sys_platform != "win32"
Dynamic: license-file
